Metadata-Version: 1.0
Name: carrot-pack
Version: 0.1.0
Summary: This package includes carrots only
Home-page: UNKNOWN
Author: Evka Marchevka
Author-email: karasewa@gmail.com
License: UNKNOWN
Platform: UNKNOWN
